{
  "workouts": [
    {
      "id": "4a3d9aaa-608c-49a7-a004-66305ad4ab50",
      "name": "Dead Push-Ups",
      "mode": "AMRAP 10",
      "equipment": [
        "barbell"
      ],
      "exercises": [
        "15 deadlifts",
        "15 hand-release push-ups"
      ],
      "createdAt": "1/25/2022, 1:15:44 PM",
      "updatedAt": "3/10/2022, 8:21:56 AM",
      "trainerTips": [
        "Deadlifts are meant to be light and fast",
        "Try to aim for unbroken sets",
        "RX Weights: 135lb/95lb"
      ]
    },
    {
      "id": "d8be2362-7b68-4ea4-a1f6-03f8bc4eede7",
      "name": "Heavy DT",
      "mode": "5 Rounds For Time",
      "equipment": [
        "barbell",
        "rope"
      ],
      "exercises": [
        "12 deadlifts",
        "9 hang power cleans",
        "6 push jerks"
      ],
      "createdAt": "11/20/2021, 5:39:07 PM",
      "updatedAt": "11/20/2021, 5:39:07 PM",
      "trainerTips": [
        "Aim for unbroken push jerks",
        "The first three rounds might feel terrible, but stick to it",
        "RX Weights: 205lb/145lb"
      ]
    },
    {
      "name": "actualizado",
      "mode": "hoy 10/04/24",
      "equipment": [
        "barbell",
        "rope"
      ],
      "exercises": [
        "21 thrusters",
        "12 rope climbs, 15 ft",
        "15 thrusters",
        "9 rope climbs, 15 ft",
        "9 thrusters",
        "6 rope climbs, 15 ft"
      ],
      "trainerTips": [
        "Split the 21 thrusters as needed",
        "Try to do the 9 and 6 thrusters unbroken",
        "RX Weights: 115lb/75lb"
      ],
      "id": "0d9a1ae2-3389-4234-967f-4a154e651f0b",
      "createdAt": "8/4/2024",
      "updatedAt": "8/4/2024",
      "updateAt": "10/4/2024"
    },
    {
      "id": "7262185b-104a-44cf-99bc-c6314cd3f316",
      "createdAt": "10/4/2024",
      "updatedAt": "10/4/2024"
    },
    {
      "name": "Tommy",
      "mode": "For Tim",
      "equipment": [
        "barbell",
        "rope"
      ],
      "exercises": [
        "21 thrusters",
        "12 rope climbs, 15 ft",
        "15 thrusters",
        "9 rope climbs, 15 ft",
        "9 thrusters",
        "6 rope climbs, 15 ft"
      ],
      "trainerTips": [
        "Split the 21 thrusters as needed",
        "Try to do the 9 and 6 thrusters unbroken",
        "RX Weights: 115lb/75lb"
      ],
      "id": "221f35c6-d3b2-41b4-8271-c4fe19417ff1",
      "createdAt": "10/4/2024",
      "updatedAt": "10/4/2024"
    }
  ]
}